easyEEG/.gitattributes
easyEEG/.gitignore
easyEEG/LICENSE
easyEEG/README.md
easyEEG/__init__.py
easyEEG/default.py
easyEEG/group.py
easyEEG/mkdocs.yml
easyEEG/structure.py
easyEEG/__pycache__/__init__.cpython-36.pyc
easyEEG/__pycache__/default.cpython-36.pyc
easyEEG/__pycache__/group.cpython-36.pyc
easyEEG/__pycache__/structure.cpython-36.pyc
easyEEG/algorithms/__init__.py
easyEEG/algorithms/basic.py
easyEEG/algorithms/classification_models.py
easyEEG/algorithms/cluster_models.py
easyEEG/algorithms/cosine_distance_models.py
easyEEG/algorithms/erp.py
easyEEG/algorithms/other.py
easyEEG/algorithms/spectrum.py
easyEEG/algorithms/topo.py
easyEEG/algorithms/__pycache__/__init__.cpython-36.pyc
easyEEG/algorithms/__pycache__/basic.cpython-36.pyc
easyEEG/algorithms/__pycache__/classification_models.cpython-36.pyc
easyEEG/algorithms/__pycache__/classifier.cpython-36.pyc
easyEEG/algorithms/__pycache__/cluster_models.cpython-36.pyc
easyEEG/algorithms/__pycache__/clustering.cpython-36.pyc
easyEEG/algorithms/__pycache__/cosine_distance_methods.cpython-36.pyc
easyEEG/algorithms/__pycache__/cosine_distance_models.cpython-36.pyc
easyEEG/algorithms/__pycache__/erp.cpython-36.pyc
easyEEG/algorithms/__pycache__/general.cpython-36.pyc
easyEEG/algorithms/__pycache__/gfp.cpython-36.pyc
easyEEG/algorithms/__pycache__/other.cpython-36.pyc
easyEEG/algorithms/__pycache__/similiarity.cpython-36.pyc
easyEEG/algorithms/__pycache__/spectrum.cpython-36.pyc
easyEEG/algorithms/__pycache__/tanova.cpython-36.pyc
easyEEG/algorithms/__pycache__/topo.cpython-36.pyc
easyEEG/data/montages/standard-10-5-cap385.elp
easyEEG/docs/api.md
easyEEG/docs/api_template.txt
easyEEG/docs/changelog.md
easyEEG/docs/cookbook.md
easyEEG/docs/cookbook_template.txt
easyEEG/docs/docs_generator.py
easyEEG/docs/index.md
easyEEG/docs/quickstart.md
easyEEG/docs/quickstart_template.txt
easyEEG/docs/tip.md
easyEEG/graph/__init__.py
easyEEG/graph/figure_group.py
easyEEG-0.8.4.1.dist-info/DESCRIPTION.rst
easyEEG-0.8.4.1.dist-info/METADATA
easyEEG-0.8.4.1.dist-info/RECORD
easyEEG-0.8.4.1.dist-info/WHEEL
easyEEG-0.8.4.1.dist-info/metadata.json
easyEEG-0.8.4.1.dist-info/top_level.txt
