Metadata-Version: 2.0
Name: easyEEG
Version: 0.8.4.1
Summary: Concise, agile, and flexible EEG toolbox
Home-page: UNKNOWN
Author: Jinbiao Yang
Author-email: ray306@gmail.com
License: GPL License
Requires-Dist: numpy
Requires-Dist: pandas
Requires-Dist: scipy
Requires-Dist: matplotlib
Requires-Dist: statsmodels
Requires-Dist: seaborn
Requires-Dist: mne
Requires-Dist: permute
Requires-Dist: tqdm
Requires-Dist: ipdb
